mais/__init__.py
mais/config.py
mais/application/__init__.py
mais/application/mais_facade.py
mais/application/builders/__init__.py
mais/application/builders/sbom_command_builder.py
mais/application/factories/__init__.py
mais/application/factories/mais_factory.py
mais/application/services/__init__.py
mais/application/services/model_analysis_service.py
mais/application/services/model_session_service.py
mais/application/services/python_ast_analyzer.py
mais/application/services/risk_assessment_service.py
mais/bin/manifest
mais/bin/manifest-cli
mais/domain/__init__.py
mais/domain/exceptions/__init__.py
mais/domain/exceptions/exceptions.py
mais/domain/model_analysis/__init__.py
mais/domain/model_analysis/entities/__init__.py
mais/domain/model_analysis/entities/model_risk_assessment.py
mais/domain/model_analysis/repositories/__init__.py
mais/domain/model_analysis/repositories/model_repository.py
mais/domain/model_analysis/value_objects/__init__.py
mais/domain/model_analysis/value_objects/model_id.py
mais/domain/model_analysis/value_objects/model_metadata.py
mais/domain/model_analysis/value_objects/risk_level.py
mais/domain/sbom/__init__.py
mais/domain/sbom/value_objects/__init__.py
mais/domain/sbom/value_objects/sbom_format.py
mais/infrastructure/__init__.py
mais/infrastructure/api/__init__.py
mais/infrastructure/api/mosaic_model_repository.py
mais/presentation/__init__.py
mais/presentation/jupyter/__init__.py
mais/presentation/jupyter/mais_plugin.py
mais/utils/__init__.py
mais/utils/logger.py
mais/utils/notebook.py
mais/utils/sbom_generation.py
mais-0.3.2.dist-info/METADATA
mais-0.3.2.dist-info/WHEEL
mais-0.3.2.dist-info/top_level.txt
mais-0.3.2.dist-info/RECORD
