Metadata-Version: 2.4
Name: mais
Version: 0.3.2
Summary: A Jupyter-compatible plugin that detects risky ML model and dataset loads.
Author-email: Daniel Bardenstein <daniel@manifestcyber.com>
Requires-Python: >=3.11
Requires-Dist: anchore-syft>=1.18.1
Requires-Dist: ipython>=7.0.0
Requires-Dist: pydantic>=2.11.7
Requires-Dist: pydantic-settings>=2.0.0
Requires-Dist: requests>=2.31.0
